LICENSE
MANIFEST.in
README.rst
setup.py
django_registration_gv.egg-info/PKG-INFO
django_registration_gv.egg-info/SOURCES.txt
django_registration_gv.egg-info/dependency_links.txt
django_registration_gv.egg-info/not-zip-safe
django_registration_gv.egg-info/top_level.txt
registration/__init__.py
registration/admin.py
registration/auth_urls.py
registration/forms.py
registration/models.py
registration/urls.py
registration/views.py
registration/management/__init__.py
registration/management/commands/__init__.py
registration/management/commands/cleanupregistration.py
registration/migrations/0001_initial.py
registration/migrations/__init__.py
registration/templates/registration/activation_complete.html
registration/templates/registration/activation_failed.html
registration/templates/registration/login.html
registration/templates/registration/logout.html
registration/templates/registration/register.html
registration/templates/registration/registration_complete.html
registration/templates/registration/email/activation_email.html
registration/templates/registration/email/activation_email.txt
registration/templates/registration/email/activation_email_subject.txt
registration/tests/__init__.py
registration/tests/test_forms.py
registration/tests/test_models.py
registration/tests/test_views.py